{
  "id": "167471",
  "source": "잡코리아",
  "url": "https://www.jobkorea.co.kr/starter/PassAssay/View/167471?Page=25&OrderBy=0&FavorCo_Stat=0&schPart=10031&Pass_An_Stat=0",
  "crawled_at": "2026-02-20T06:35:31.661804Z",
  "company": "엔테크서비스(주)",
  "position": "인턴 앱개발자",
  "year": "2016년 상반기",
  "questions": [
    {
      "question": "SW 개발 관련하여 수강한 과목명 및 성적을 연도별로 구분하여 작성해 주세요. (자료구조, 알고리즘, 개발 언어 성적 우수자 우대합니다.)",
      "answer": "[2012년 상반기]\r\n \n자료구조 A+\r\n논리회로 B+\r\n \n[2012년 하반기]\r\n \n컴퓨터구조 A+\r\n시스템분석과 설계 A+\r\n자바프로그래밍 A+\r\n \n[2013년 상반기]\r\n \n데이터베이스 A+\r\n컴퓨터 네트워크 A+\r\n컴퓨터 개론 B+\r\n운영체제 A+\r\n객체지향 프로그래밍 A+\r\n모바일인터페이스 디자인 B+\r\n \n[2013년 하반기]\r\n \n데이터베이스 프로그래밍 A+\r\n프로그래밍 응용 및 실습 A+\r\n프로그래밍 언어론 A+\r\n소프트웨어 공학 A+\r\n인공지능 A+\r\n시스템 프로그래밍 A+\r\n \n[2015년 상반기]\r\n \n모바일프로그래밍 A+\r\n컴퓨터 알고리즘 A+\r\n컴퓨터공학 캡스톤디자인 A+\r\n프로그래밍언어  A+\r\n스마트모바일 개론 A+\r\n \n[2015년 하반기]\r\n \n웹어플리케이션 구축 A+\r\n컴퓨터공학 인턴십 A+\r\n모바일 프로그래밍  A+\r\n센서네트워크 A+"
    },
    {
      "question": "SW 개발 관련하여 성공 혹은 실패한 프로젝트가 있다면, 왜 성공/실패했다고 판단했는지와 그 요인을 기술해 주세요. (10줄 이내)",
      "answer": "[에너지 절약 APP]\r\n \n에너지 해커톤 대회에서 시간적 한계에 부딪혔지만 포기하지 않고 창의적인 발상을 한 경험이 있습니다. 시간 내에 완성하여 에너지 해커톤 대상을 받았습니다. 해커톤에서 성공한 이유는 2가지라고 생각합니다.\r\n \n첫번째, 남들과 다른 창의성\r\n팀원들과 함께 고심한 끝에 가정의 전기 사용량을 스마트폰으로 미리 확인해서 계획적으로 전기 사용을 할 수 있는 APP을 제작하는 것이었습니다. 하지만 평범한 생각보다 우리에게 필요하고 색다른 기능을 추가할 것을 생각했습니다. 그래서 저희는 전자기기를 잘 사용하지 못하는 노인분들과 시각장애인을 위해 ARS 기능을 추가하여 현재 사용한 전력에 따라 사용한 금액을 음성으로 알려줄 수 있는 기능을 구현하기로 했습니다. 이렇게 좀더 창의적으로 생각해서 남들과 다른 아이템을 구현했기 때문에 경쟁력이 있었다고 생각합니다.\r\n \n두번째, 전문지식에 기반한 IT경험\r\n아무리 좋은 설계도가 있다고 해도 건물을 짓는 재료가 좋지 않다면 건물은 금방 무너져 내릴 것입니다. 그래서 기본 지식이 큰 성공의 밑거름이라 생각합니다. 이전에 기초를 열심히 다져서 전공 학점 4.3의 좋은 점수를 받았습니다. 이를 기초로 많은 제작한 프로그램을 가지고 교내 학술 대회에서 우수상 획득, 캡스톤 디자인 우수상, 에너지 해커톤 대상, OCP DBA 자격을 받았습니다. 이러한 탄탄한 전문지식을 바탕이 있었기에 아이디어를 구현할 수 있었다고 생각합니다.\r\n \n앞으로 NHN Technology Services에 입사 후에도 이러한 스마트한 기술과 창의적인 생각으로 완성도 높은 서비스를 제공하도록 노력하겠습니다."
    },
    {
      "question": "분 자기소개를 해보세요.\n\n\n면접",
      "answer": ""
    }
  ],
  "expert_feedback": null
}