{
  "id": "188497",
  "source": "잡코리아",
  "url": "https://www.jobkorea.co.kr/starter/PassAssay/View/188497?Page=22&OrderBy=0&FavorCo_Stat=0&schPart=10031&Pass_An_Stat=0",
  "crawled_at": "2026-02-20T06:33:55.374419Z",
  "company": "(주)한글과컴퓨터",
  "position": "신입 웹개발자",
  "year": "2016년 하반기",
  "questions": [
    {
      "question": "한컴이 꿈꾸는 미래, 당신이 꿈구는 미래 함께할 수 있다면 당신이 가장 중요하게 생각하는 기치의 기준은 무엇인지 구체적으로 서술하라.",
      "answer": "`첫 번째, 환경에 빠르게 적응하고, 성장해 혁신을 주도하는 인재`"
    },
    {
      "question": "한컴인이되기 위해 어떠한 마음가짐으로 어떤 준비를 했는지 혹은 하고 있는지 구체적으로 서술하라.",
      "answer": "학교에서 과제를 잘하고 성적을 잘 받는 학생으로 만족하는 것이 아니라 다양한 프로젝트 경험을 통해 `진짜 개발자`가 되기위해 노력했습니다."
    },
    {
      "question": "한컴이 당신을 선발해야 하는 이유는? 당신의 매력을 구체적으로 서술하라.",
      "answer": "저는 다음과 같은 신조를 가지고 있습니다.\r\n \n첫째 여러 분야를 경험해 보려 노력했습니다."
    }
  ],
  "expert_feedback": null
}