{
  "id": "12767",
  "source": "링커리어",
  "url": "https://linkareer.com/cover-letter/12767",
  "crawled_at": "2026-02-23T11:26:14.591875Z",
  "company": "신세계닷컴 / SW / 2018 하반기",
  "position": "",
  "year": "",
  "questions": [
    {
      "question": "당사에 지원한 이유와 입사를 위해 어떤 노력을 하였는지 구체적으로 기술하시오.",
      "answer": "저에게 있어 회사의 매력을 가장 크게 느끼는 부분은 ‘제가 그 회사와 함께 성장해나갈 수 있는가’입니다. 회사가 계속 발전하고 성장해나감으로써 그 속의 구성원들도 성장해 나갈 수 있다고 생각하기 때문입니다. ‘SSG닷컴’은 신세계몰과 이마트몰을 통합 운영하면서 실적을 냈을 뿐만 아니라 그것 이외에도 ‘신세계TV쇼핑’, ‘S.I.빌리지’ 등 그룹 주요 쇼핑몰까지 단일 온라인 플랫폼으로 통합해 시너지 효과를 내며 한층 더 성장했습니다. 최근에는 ‘e-커머스’ 법인을 설립하면서 온라인 사업부를 한데로 모아 온라인몰의 더욱 높은 성장세를 전망하고 있습니다. 또한, 단순히 웹사이트뿐만 아니라 모바일과 연계해 다양한 혜택을 제공하고 있고, 모바일에 특화된 ‘샤벳’ 앱도 선보이는 등 다양한 서비스를 고객에게 제공하기 위해 힘쓰고 있습니다."
    }
  ],
  "expert_feedback": null
}